{
  "sections": {
    "0690df70-d323-47b3-9ae6-cc57d8ebfb55": {
      "type": "slideshow",
      "blocks": {
        "template--21375543214379__0690df70-d323-47b3-9ae6-cc57d8ebfb55-slide-1": {
          "type": "slide",
          "settings": {
            "image": "shopify:\/\/shop_images\/Logo.png_Title.jpg",
            "heading": "",
            "heading_size": "h2",
            "subheading": "",
            "button_label": "Grotto Tickets",
            "link": "https:\/\/www.eventbrite.co.uk\/e\/coulsdons-santas-grotto-2023-tickets-528334842737",
            "button_style_secondary": false,
            "box_align": "middle-center",
            "show_text_box": false,
            "text_alignment": "center",
            "image_overlay_opacity": 0,
            "color_scheme": "scheme-89be9658-96f9-488d-b341-41dee1f513d9",
            "text_alignment_mobile": "center"
          }
        }
      },
      "block_order": [
        "template--21375543214379__0690df70-d323-47b3-9ae6-cc57d8ebfb55-slide-1"
      ],
      "settings": {
        "layout": "full_bleed",
        "slide_height": "medium",
        "slider_visual": "counter",
        "auto_rotate": false,
        "change_slides_speed": 5,
        "image_behavior": "none",
        "show_text_below": true,
        "accessibility_info": "Slideshow about our brand"
      }
    },
    "d3c25f90-5bfb-48a0-8053-84c6b9e48736": {
      "type": "rich-text",
      "blocks": {
        "template--21375543214379__d3c25f90-5bfb-48a0-8053-84c6b9e48736-heading-1": {
          "type": "heading",
          "settings": {
            "heading": "Welcome to Coulsdon Yuletide Magic - A Festive Celebration!",
            "heading_size": "h1"
          }
        },
        "template--21375543214379__d3c25f90-5bfb-48a0-8053-84c6b9e48736-text-1": {
          "type": "text",
          "disabled": true,
          "settings": {
            "text": "<p>Share information about your brand with your customers. Describe a product, make announcements, or welcome customers to your store.<\/p>"
          }
        },
        "template--21375543214379__d3c25f90-5bfb-48a0-8053-84c6b9e48736-button-1": {
          "type": "button",
          "disabled": true,
          "settings": {
            "button_label": "Button label",
            "button_link": "",
            "button_style_secondary": false,
            "button_label_2": "",
            "button_link_2": "",
            "button_style_secondary_2": false
          }
        }
      },
      "block_order": [
        "template--21375543214379__d3c25f90-5bfb-48a0-8053-84c6b9e48736-heading-1",
        "template--21375543214379__d3c25f90-5bfb-48a0-8053-84c6b9e48736-text-1",
        "template--21375543214379__d3c25f90-5bfb-48a0-8053-84c6b9e48736-button-1"
      ],
      "settings": {
        "desktop_content_position": "center",
        "content_alignment": "center",
        "color_scheme": "scheme-89be9658-96f9-488d-b341-41dee1f513d9",
        "full_width": true,
        "padding_top": 40,
        "padding_bottom": 52
      }
    },
    "69754ee3-c5f9-470e-a684-21e9c25658f4": {
      "type": "rich-text",
      "blocks": {
        "3f0261ef-def1-4244-81a9-1ee8ce1e8980": {
          "type": "caption",
          "settings": {
            "caption": "Starts at {{ metaobject.start | metafield_text }} to {{ metaobject.end | metafield_text }}",
            "text_style": "caption-with-letter-spacing",
            "text_size": "large"
          }
        },
        "template--20538124271915__69754ee3-c5f9-470e-a684-21e9c25658f4-text-1": {
          "type": "text",
          "settings": {
            "text": "{{ metaobject.description | metafield_tag }}"
          }
        }
      },
      "block_order": [
        "3f0261ef-def1-4244-81a9-1ee8ce1e8980",
        "template--20538124271915__69754ee3-c5f9-470e-a684-21e9c25658f4-text-1"
      ],
      "settings": {
        "desktop_content_position": "center",
        "content_alignment": "center",
        "color_scheme": "scheme-89be9658-96f9-488d-b341-41dee1f513d9",
        "full_width": true,
        "padding_top": 16,
        "padding_bottom": 20
      }
    },
    "4fe1e120-8b87-4d2c-b808-2bd4f8fd103e": {
      "type": "custom-liquid",
      "settings": {
        "custom_liquid": "<div id=\"eventbrite-widget-container\"><\/div>\n\n<script src=\"https:\/\/www.eventbrite.co.uk\/static\/widgets\/eb_widgets.js\"><\/script>\n\n<script type=\"text\/javascript\">\n    var exampleCallback = window.EBWidgets.createWidget({\n        \/\/ Required\n        widgetType: 'checkout',\n        eventId: '{{ metaobject.eventbrite_id.value }}',\n        iframeContainerId: 'eventbrite-widget-container',\n    });\n<\/script",
        "color_scheme": "",
        "padding_top": 40,
        "padding_bottom": 52
      }
    }
  },
  "order": [
    "0690df70-d323-47b3-9ae6-cc57d8ebfb55",
    "d3c25f90-5bfb-48a0-8053-84c6b9e48736",
    "69754ee3-c5f9-470e-a684-21e9c25658f4",
    "4fe1e120-8b87-4d2c-b808-2bd4f8fd103e"
  ]
}
